{
"type": "FeatureCollection",
"name": "campioni",
"crs": { "type": "name", "properties": { "name": "urn:ogc:def:crs:OGC:1.3:CRS84" } },
"features": [
{ "type": "Feature", "properties": { "campioni": "C" }, "geometry": { "type": "Point", "coordinates": [ -0.012153, 51.678105 ] } },
{ "type": "Feature", "properties": { "campioni": "D" }, "geometry": { "type": "Point", "coordinates": [ 0.031002, 51.599256 ] } },
{ "type": "Feature", "properties": { "campioni": "B2" }, "geometry": { "type": "Point", "coordinates": [ -0.12313, 51.596618 ] } },
{ "type": "Feature", "properties": { "campioni": "E1" }, "geometry": { "type": "Point", "coordinates": [ -0.040007, 51.498769 ] } },
{ "type": "Feature", "properties": { "campioni": "A3" }, "geometry": { "type": "Point", "coordinates": [ -0.0806, 51.5708 ] } },
{ "type": "Feature", "properties": { "campioni": "A2" }, "geometry": { "type": "Point", "coordinates": [ -0.104654, 51.573901 ] } },
{ "type": "Feature", "properties": { "campioni": "F" }, "geometry": { "type": "Point", "coordinates": [ -0.038, 51.5609 ] } },
{ "type": "Feature", "properties": { "campioni": "G" }, "geometry": { "type": "Point", "coordinates": [ -0.014165, 51.545884 ] } }
]
}
